LICENSE
MANIFEST.in
README.md
setup.py
aguiardafa_libpythonpro.egg-info/PKG-INFO
aguiardafa_libpythonpro.egg-info/SOURCES.txt
aguiardafa_libpythonpro.egg-info/dependency_links.txt
aguiardafa_libpythonpro.egg-info/not-zip-safe
aguiardafa_libpythonpro.egg-info/requires.txt
aguiardafa_libpythonpro.egg-info/top_level.txt
libpythonpro/__init__.py
libpythonpro/githubapi.py
libpythonpro/spam/__init__.py
libpythonpro/spam/db.py
libpythonpro/spam/enviador_de_email.py
libpythonpro/spam/main.py
libpythonpro/spam/models.py
libpythonpro/tests/__init__.py
libpythonpro/tests/test_exemplo_pytest.py
libpythonpro/tests/test_githubapi_pytest.py
libpythonpro/tests/test_spam/__init__.py
libpythonpro/tests/test_spam/conftest.py
libpythonpro/tests/test_spam/test_enviador_de_email.py
libpythonpro/tests/test_spam/test_envio_para_base_de_usuarios.py
libpythonpro/tests/test_spam/test_envio_para_base_de_usuarios_com_libmock.py
libpythonpro/tests/test_spam/test_usuarios.py